topsis_riddham/__init__.py
topsis_riddham/topsis.py
Topsis_Ridham_102216019-0.1.1.dist-info/METADATA
Topsis_Ridham_102216019-0.1.1.dist-info/WHEEL
Topsis_Ridham_102216019-0.1.1.dist-info/entry_points.txt
Topsis_Ridham_102216019-0.1.1.dist-info/top_level.txt
Topsis_Ridham_102216019-0.1.1.dist-info/RECORD
