Metadata-Version: 2.1
Name: Topsis-Ridham-102216019
Version: 0.1.1
Summary: A Python package to perform TOPSIS analysis
Author: Riddham Uppal
Author-email: varora2004@gmail.com
Classifier: Programming Language :: Python :: 3
Classifier: License :: OSI Approved :: MIT License
Classifier: Operating System :: OS Independent
Requires-Python: >=3.6
Requires-Dist: numpy
Requires-Dist: pandas
